ptsemseg
