Metadata-Version: 1.1
Name: pytorch-semseg
Version: 0.1.2
Summary: Semantic Segmentation Architectures implemented in PyTorch
Home-page: https://github.com/meetshah1995/pytorch-semseg
Author: Meet Pragnesh Shah
Author-email: meetshah1995@gmail.com
License: MIT
Keywords: semantic-segmentation,fully-convolutional-networks,deep-learning,pytorch
Platform: UNKNOWN
Classifier: Development Status :: 4 - Beta
Classifier: License :: OSI Approved :: MIT License
Classifier: Programming Language :: Python :: 2.7
Classifier: Intended Audience :: Science/Research
Classifier: Topic :: Scientific/Engineering :: Artificial Intelligence
